{
  "initial_capital": 1000.0,
  "effective_capital": 1019.19,
  "current_capital": 1023.7456,
  "peak_capital": 1023.7456,
  "positions": [
    {
      "coin": "BTC",
      "direction": "LONG",
      "order_type": "LIMIT_BUY",
      "limit_price": 79577.76,
      "entry_zone_low": 79175.37,
      "entry_zone_high": 79980.14,
      "entry_price": null,
      "current_price": 80645.76,
      "quantity": 0.01394636,
      "leverage": 3,
      "margin": 369.94,
      "notional": 1109.82,
      "weight_pct": 37.0,
      "prob_score": 67,
      "tp1": 80562.79,
      "tp2": 81754.05,
      "sl": 78848.43,
      "status": "PENDING",
      "placed_at": "2026-05-11T07:02:37.816110+00:00",
      "expires_at": "2026-05-16T07:02:37.816119+00:00",
      "filled_at": null,
      "closed_at": null,
      "pnl_usd": 0.0,
      "pnl_pct": 0.0,
      "max_profit_usd": 0.0,
      "max_loss_usd": 0.0,
      "close_reason": null,
      "_fill_hint": "↘1.5%"
    },
    {
      "coin": "SOL",
      "direction": "SHORT",
      "order_type": "LIMIT_SELL",
      "limit_price": 95.43,
      "entry_zone_low": 94.9529,
      "entry_zone_high": 95.9072,
      "entry_price": 95.43,
      "current_price": 94.97,
      "quantity": 9.90348947,
      "leverage": 3,
      "margin": 315.03,
      "notional": 945.09,
      "weight_pct": 31.5,
      "prob_score": 35,
      "tp1": 92.853,
      "tp2": 88.0593,
      "sl": 98.9204,
      "status": "OPEN",
      "placed_at": "2026-05-11T07:02:37.816110+00:00",
      "expires_at": "2026-05-16T07:02:37.816119+00:00",
      "filled_at": "2026-05-11T07:02:51.327979+00:00",
      "closed_at": null,
      "pnl_usd": 4.5556,
      "pnl_pct": 1.45,
      "max_profit_usd": 4.5556,
      "max_loss_usd": -22.3819,
      "close_reason": null,
      "_fill_hint": "✅即时",
      "open_fee": 0.189
    },
    {
      "coin": "TAO",
      "direction": "SHORT",
      "order_type": "LIMIT_SELL",
      "limit_price": 318.456,
      "entry_zone_low": 316.8637,
      "entry_zone_high": 320.0483,
      "entry_price": 318.456,
      "current_price": 311.8,
      "quantity": 2.96772553,
      "leverage": 3,
      "margin": 315.03,
      "notional": 945.09,
      "weight_pct": 31.5,
      "prob_score": 35,
      "tp1": 312.8955,
      "tp2": 300.7963,
      "sl": 332.1564,
      "status": "CLOSED_TP1",
      "placed_at": "2026-05-11T07:02:37.816110+00:00",
      "expires_at": "2026-05-16T07:02:37.816119+00:00",
      "filled_at": "2026-05-11T07:02:51.327979+00:00",
      "closed_at": "2026-05-12T14:17:19.564195+00:00",
      "pnl_usd": 19.5681,
      "pnl_pct": 6.21,
      "max_profit_usd": 19.7532,
      "max_loss_usd": -24.7627,
      "close_reason": "✅ TP1触发 @$311.8000",
      "_fill_hint": "✅即时",
      "open_fee": 0.189,
      "close_fee": 0.1851,
      "total_fee": 0.3741
    }
  ],
  "created_at": "2026-05-11T07:02:37.816110+00:00",
  "last_updated": "2026-05-12T14:17:19.564195+00:00",
  "signal_generated": "2026-05-11T07:02:05.651122+00:00",
  "order_ttl_days": 5,
  "risk_config": {
    "max_drawdown_pct": 3.0,
    "profit_target_min_pct": 5.0,
    "profit_target_max_pct": 10.0,
    "min_prob_score": 10,
    "leverage_multiplier": 1.0,
    "max_position_weight": 0.3,
    "min_position_weight": 0.1
  },
  "risk_mode": false,
  "profit_lock_mode": false,
  "current_drawdown_pct": 0.0,
  "total_trades": 1,
  "total_wins": 1,
  "total_losses": 0,
  "realized_pnl": 19.1901,
  "optimization_log": [
    {
      "date": "2026-05-11",
      "changes": [
        "📌 成交率0% < 60%：建议调整挂单价至 entry_zone 边界以提高成交率"
      ],
      "stats": {
        "total": 5,
        "closed": 0,
        "cancelled": 5,
        "fill_rate": 0.0,
        "sl_rate": 0,
        "cancel_rate": 100.0,
        "win_rate": 0.0,
        "avg_win": 0.0,
        "avg_loss": 0.0,
        "total_pnl": 0.0
      }
    }
  ],
  "total_fees": 0.3741
}